xed/__init__.py
xed/xed.py
xed-0.0.5.dist-info/LICENSE
xed-0.0.5.dist-info/METADATA
xed-0.0.5.dist-info/WHEEL
xed-0.0.5.dist-info/entry_points.txt
xed-0.0.5.dist-info/top_level.txt
xed-0.0.5.dist-info/RECORD
